EZ/__init__.py
EZ/config.py
py_ezconfig-0.0.1.dist-info/METADATA
py_ezconfig-0.0.1.dist-info/WHEEL
py_ezconfig-0.0.1.dist-info/top_level.txt
py_ezconfig-0.0.1.dist-info/RECORD
