Metadata-Version: 2.1
Name: py-ezconfig
Version: 0.0.1
Summary: EZ Functionality
Home-page: UNKNOWN
Author: LainUp Computer
Author-email: info@lainupcomputersolution.de
License: UNKNOWN
Keywords: python
Platform: UNKNOWN
Classifier: Development Status :: 1 - Planning
Classifier: Intended Audience :: Developers
Classifier: Programming Language :: Python :: 3
Classifier: Operating System :: Unix
Classifier: Operating System :: MacOS :: MacOS X
Classifier: Operating System :: Microsoft :: Windows
